confectioner/__init__.py
confectioner/_version.py
confectioner/baker.py
confectioner/core.py
confectioner/exceptions.py
confectioner/files.py
confectioner/py.typed
confectioner/templating.py
confectioner-1.1.0.dist-info/METADATA
confectioner-1.1.0.dist-info/WHEEL
confectioner-1.1.0.dist-info/licenses/LICENSE
confectioner-1.1.0.dist-info/RECORD
